{
  "schemaVersion": 1,
  "skill": "retention",
  "items": [
    {
      "taskId": "task-104",
      "taskTitle": "Рассчитать D7/D30 retention и объяснить разницу между активацией и удержанием",
      "sourceType": "main",
      "section": "Месяц 6: Продуктовая и банковская аналитика",
      "skill": {
        "id": "retention",
        "title": "Retention-аналитика"
      },
      "modules": [
        {
          "id": "5.5",
          "title": "SQL Investigation"
        },
        {
          "id": "5.6",
          "title": "Business Simulator"
        }
      ],
      "practiceContent": {
        "businessContext": "Мобильный финтех-сервис Finova работает на рынках Казахстана и Кыргызстана: p2p-переводы, кошелёк, кредитная линия. Команда аналитики видит рост регистраций, но нет ясности, что именно двигает бизнес вперёд. Число пользователей растёт, но продакт замечает: MAU стагнирует, хотя новые регистрации сильные. Аналитик должен разобраться с retention.",
        "managerRequest": "Посчитай D7 и D30 retention по когортам. Объясни разницу между activation rate (первая ценная активность ≤7д) и retention rate (вернулись через 30д). Покажи, какой показатель важнее для прогноза MAU.",
        "businessGoal": "Понять, почему MAU не растёт при росте регистраций — чтобы направить ресурсы в нужное место.",
        "inputData": {
          "description": "Выгрузки из продуктовой аналитики, CRM и BI-витрин.",
          "tables": [
            {
              "name": "events",
              "fields": [
                "user_id",
                "event_name",
                "event_ts"
              ],
              "source": "продуктовая аналитика"
            },
            {
              "name": "users",
              "fields": [
                "user_id",
                "signup_date",
                "channel",
                "plan"
              ],
              "source": "CRM"
            }
          ],
          "sources": [
            "продуктовая аналитика",
            "CRM"
          ]
        },
        "analystTask": [
          "Определить 'активацию': пользователь совершил первую транзакцию в течение 7 дней после регистрации.",
          "Посчитать activation rate по когортам (неделям регистрации).",
          "Посчитать D7 и D30 retention: доля пользователей когорты, вернувшихся на 7-й и 30-й день.",
          "Объяснить: если activation rate = 20%, что это означает для MAU при регистрациях 1000/нед?"
        ],
        "expectedResult": "Когортная таблица retention (строки = когорты, столбцы = D1/D7/D30) и краткий вывод.",
        "businessConclusion": "Нашли: проблема не в привлечении, а в активации — 80% не совершают первой транзакции. Чинить онбординг важнее, чем наращивать рекламный бюджет.",
        "validationCriteria": [
          "Retention считается по когортам, не общим агрегатом.",
          "Activation ≠ Retention — разница объяснена.",
          "Вывод содержит прогноз MAU."
        ],
        "commonMistakes": [
          "Считать retention как 'процент активных за месяц' — это active rate, не cohort retention.",
          "Не привязать activation к первой ценной активности — выбрать неправильное событие."
        ],
        "skills": [
          "retention",
          "когортный анализ",
          "активация",
          "продуктовые метрики",
          "SQL"
        ],
        "difficulty": "medium",
        "estimatedTime": 110,
        "hiringSignal": "Работодатель проверяет: умеет ли кандидат считать retention правильно (по когортам) и объяснить разницу активация/удержание без жаргона.",
        "portfolioValue": {
          "canUse": true,
          "note": "Да, если оформить как мини-кейс с бизнес-вопросом, данными и выводом."
        },
        "interviewQuestions": [
          "Чем cohort retention отличается от simple retention?",
          "Как выбрать 'aha moment' для расчёта activation?",
          "Если D7 retention = 40%, как это читать для бизнеса?"
        ]
      }
    }
  ]
}