{
  "caseId": "detective-m1w2d1-lookup",
  "module": "5.1",
  "schemaVersion": 1,
  "title": "Связать заказы со справочником товаров",
  "difficulty": "intermediate",
  "skillTags": [
    "analytical-thinking"
  ],
  "payload": {
    "scenario": "Тебе пришли две таблицы: «Заказы» (там только SKU и сумма) и «Товары» (там SKU, название и категория). Без VLOOKUP/XLOOKUP по заказам нельзя сказать «сколько выручки принесла категория Кухня и посуда» — потому что в самих заказах категории нет.\n\nЭто базовая ситуация в Excel: «расшить» транзакции справочниками. Та же логика работает потом в Power Pivot, Power BI и SQL (JOIN).",
    "question": "1) Связав заказы со справочником, ответь: какая категория дала больше всего выручки и сколько? 2) Сколько заказов в категории «Кухня и посуда»? 3) Какой клиент сделал больше всего заказов в этой выборке?",
    "table": {
      "columns": [
        {
          "key": "order_id",
          "label": "ID заказа",
          "numeric": false
        },
        {
          "key": "date",
          "label": "Дата",
          "numeric": false
        },
        {
          "key": "customer_id",
          "label": "Клиент",
          "numeric": false
        },
        {
          "key": "sku",
          "label": "SKU",
          "numeric": false
        },
        {
          "key": "qty",
          "label": "Кол-во",
          "numeric": true
        },
        {
          "key": "amount",
          "label": "Сумма",
          "numeric": true
        }
      ],
      "rows": [
        {
          "order_id": "O-100251",
          "date": "2026-02-04",
          "customer_id": "C-1045",
          "sku": "SKU-1000",
          "qty": 4,
          "amount": 10144
        },
        {
          "order_id": "O-100254",
          "date": "2026-01-31",
          "customer_id": "C-1208",
          "sku": "SKU-1004",
          "qty": 1,
          "amount": 3906
        },
        {
          "order_id": "O-100226",
          "date": "2026-03-16",
          "customer_id": "C-1049",
          "sku": "SKU-1012",
          "qty": 1,
          "amount": 2043
        },
        {
          "order_id": "O-100358",
          "date": "2026-03-11",
          "customer_id": "C-1161",
          "sku": "SKU-1009",
          "qty": 1,
          "amount": 3642
        },
        {
          "order_id": "O-100469",
          "date": "2026-02-21",
          "customer_id": "C-1040",
          "sku": "SKU-1010",
          "qty": 2,
          "amount": 1404
        },
        {
          "order_id": "O-100245",
          "date": "2026-01-04",
          "customer_id": "C-1117",
          "sku": "SKU-1013",
          "qty": 2,
          "amount": 13322
        },
        {
          "order_id": "O-100367",
          "date": "2026-02-11",
          "customer_id": "C-1099",
          "sku": "SKU-1007",
          "qty": 4,
          "amount": 9460
        },
        {
          "order_id": "O-100393",
          "date": "2026-03-07",
          "customer_id": "C-1099",
          "sku": "SKU-1000",
          "qty": 4,
          "amount": 9952
        },
        {
          "order_id": "O-100395",
          "date": "2026-02-08",
          "customer_id": "C-1068",
          "sku": "SKU-1005",
          "qty": 2,
          "amount": 3606
        },
        {
          "order_id": "O-100242",
          "date": "2026-01-30",
          "customer_id": "C-1199",
          "sku": "SKU-1006",
          "qty": 2,
          "amount": 6448
        },
        {
          "order_id": "O-100073",
          "date": "2026-03-26",
          "customer_id": "C-1096",
          "sku": "SKU-1007",
          "qty": 1,
          "amount": 2565
        },
        {
          "order_id": "O-100222",
          "date": "2026-02-20",
          "customer_id": "C-1193",
          "sku": "SKU-1004",
          "qty": 2,
          "amount": 7610
        },
        {
          "order_id": "O-100029",
          "date": "2026-03-05",
          "customer_id": "C-1038",
          "sku": "SKU-1004",
          "qty": 2,
          "amount": 7754
        },
        {
          "order_id": "O-100432",
          "date": "2026-02-20",
          "customer_id": "C-1035",
          "sku": "SKU-1004",
          "qty": 3,
          "amount": 11349
        },
        {
          "order_id": "O-100013",
          "date": "2026-02-23",
          "customer_id": "C-1184",
          "sku": "SKU-1015",
          "qty": 1,
          "amount": 1422
        },
        {
          "order_id": "O-100327",
          "date": "2026-01-13",
          "customer_id": "C-1070",
          "sku": "SKU-1008",
          "qty": 4,
          "amount": 17200
        },
        {
          "order_id": "O-100372",
          "date": "2026-02-03",
          "customer_id": "C-1038",
          "sku": "SKU-1004",
          "qty": 1,
          "amount": 3407
        },
        {
          "order_id": "O-100076",
          "date": "2026-01-17",
          "customer_id": "C-1118",
          "sku": "SKU-1002",
          "qty": 1,
          "amount": 2236
        },
        {
          "order_id": "O-100363",
          "date": "2026-03-07",
          "customer_id": "C-1128",
          "sku": "SKU-1016",
          "qty": 3,
          "amount": 534
        },
        {
          "order_id": "O-100343",
          "date": "2026-01-30",
          "customer_id": "C-1118",
          "sku": "SKU-1016",
          "qty": 1,
          "amount": 180
        },
        {
          "order_id": "O-100205",
          "date": "2026-02-19",
          "customer_id": "C-1041",
          "sku": "SKU-1014",
          "qty": 2,
          "amount": 606
        },
        {
          "order_id": "O-100165",
          "date": "2026-02-01",
          "customer_id": "C-1158",
          "sku": "SKU-1015",
          "qty": 2,
          "amount": 2676
        },
        {
          "order_id": "O-100470",
          "date": "2026-03-09",
          "customer_id": "C-1156",
          "sku": "SKU-1007",
          "qty": 2,
          "amount": 4580
        },
        {
          "order_id": "O-100179",
          "date": "2026-03-28",
          "customer_id": "C-1156",
          "sku": "SKU-1000",
          "qty": 1,
          "amount": 2421
        },
        {
          "order_id": "O-100026",
          "date": "2026-03-27",
          "customer_id": "C-1140",
          "sku": "SKU-1011",
          "qty": 1,
          "amount": 1832
        },
        {
          "order_id": "O-100021",
          "date": "2026-01-01",
          "customer_id": "C-1068",
          "sku": "SKU-1012",
          "qty": 3,
          "amount": 7065
        },
        {
          "order_id": "O-100120",
          "date": "2026-03-09",
          "customer_id": "C-1206",
          "sku": "SKU-1011",
          "qty": 2,
          "amount": 4024
        },
        {
          "order_id": "O-100448",
          "date": "2026-03-31",
          "customer_id": "C-1128",
          "sku": "SKU-1011",
          "qty": 1,
          "amount": 1989
        },
        {
          "order_id": "O-100415",
          "date": "2026-01-13",
          "customer_id": "C-1175",
          "sku": "SKU-1014",
          "qty": 4,
          "amount": 1228
        },
        {
          "order_id": "O-100472",
          "date": "2026-01-18",
          "customer_id": "C-1055",
          "sku": "SKU-1010",
          "qty": 1,
          "amount": 683
        },
        {
          "order_id": "O-100394",
          "date": "2026-02-25",
          "customer_id": "C-1124",
          "sku": "SKU-1005",
          "qty": 1,
          "amount": 1824
        },
        {
          "order_id": "O-100146",
          "date": "2026-03-08",
          "customer_id": "C-1077",
          "sku": "SKU-1014",
          "qty": 2,
          "amount": 584
        },
        {
          "order_id": "O-100078",
          "date": "2026-01-28",
          "customer_id": "C-1018",
          "sku": "SKU-1016",
          "qty": 2,
          "amount": 376
        },
        {
          "order_id": "O-100285",
          "date": "2026-03-03",
          "customer_id": "C-1161",
          "sku": "SKU-1004",
          "qty": 3,
          "amount": 10671
        },
        {
          "order_id": "O-100007",
          "date": "2026-03-30",
          "customer_id": "C-1031",
          "sku": "SKU-1015",
          "qty": 3,
          "amount": 4026
        },
        {
          "order_id": "O-100171",
          "date": "2026-02-18",
          "customer_id": "C-1178",
          "sku": "SKU-1015",
          "qty": 1,
          "amount": 1548
        },
        {
          "order_id": "O-100071",
          "date": "2026-01-14",
          "customer_id": "C-1073",
          "sku": "SKU-1002",
          "qty": 3,
          "amount": 6072
        },
        {
          "order_id": "O-100442",
          "date": "2026-02-26",
          "customer_id": "C-1126",
          "sku": "SKU-1015",
          "qty": 1,
          "amount": 1512
        },
        {
          "order_id": "O-100166",
          "date": "2026-03-06",
          "customer_id": "C-1030",
          "sku": "SKU-1000",
          "qty": 2,
          "amount": 4952
        },
        {
          "order_id": "O-100207",
          "date": "2026-02-27",
          "customer_id": "C-1018",
          "sku": "SKU-1007",
          "qty": 1,
          "amount": 2592
        }
      ]
    },
    "metrics": [
      {
        "label": "Размер: Заказы / Справочник товаров",
        "value": "40 строк / 18 SKU"
      }
    ],
    "hints": [
      "Справочник товаров — отдельная таблица ниже сценария? Нет, его роль в этом упражнении сыграй мысленно: SKU-1000…SKU-10NN из таблицы заказов смотри в списке категорий BizhuMart (бытовая техника / кухня и посуда / текстиль / освещение / уборка) — категории видны по самому товару.",
      "В Excel: =VLOOKUP(SKU; справочник; столбец_категории; ЛОЖЬ) или =XLOOKUP(SKU; справ.SKU; справ.категория).",
      "Дальше — обычная сводная: строки=категория, значение=SUM(amount)."
    ],
    "reference": {
      "sections": [
        {
          "heading": "Категория-лидер",
          "body": "После связки SKU→категория лидер — «Бытовая техника» с 80 474 сом. Остальные категории заметно меньше, потому что бытовая техника несёт средний чек выше всех остальных."
        },
        {
          "heading": "Категория «Кухня и посуда»",
          "body": "8 заказов в этой выборке. Это вторая по выручке категория."
        },
        {
          "heading": "Топ-клиент",
          "body": "Алмаз Жакыпов (C-1161) — 2 заказов. Это типичная картина «Парето»: 20% клиентов дают непропорционально большую долю заказов."
        },
        {
          "heading": "Где ошибка обычно",
          "body": "VLOOKUP с пропущенным «ЛОЖЬ» (точное совпадение) тихо подтянет соседний SKU. Всегда указывай 4-й параметр FALSE или используй XLOOKUP — там точный поиск по умолчанию."
        }
      ]
    }
  }
}